.gitignore
CHANGES.txt
LICENSE.txt
README.rst
bootstrap.py
buildout.cfg
setup.cfg
setup.py
etc/base.cfg
etc/versions-nonzope.cfg
src/.gitignore
src/tau/__init__.py
src/tau.selectorstrings.egg-info/PKG-INFO
src/tau.selectorstrings.egg-info/SOURCES.txt
src/tau.selectorstrings.egg-info/dependency_links.txt
src/tau.selectorstrings.egg-info/namespace_packages.txt
src/tau.selectorstrings.egg-info/not-zip-safe
src/tau.selectorstrings.egg-info/requires.txt
src/tau.selectorstrings.egg-info/top_level.txt
src/tau/selectorstrings/__init__.py
src/tau/selectorstrings/configure.zcml
src/tau/selectorstrings/interfaces.py
src/tau/selectorstrings/meta.zcml
src/tau/selectorstrings/zcml_directives.py