Metadata-Version: 1.0
Name: tau.selectorstrings
Version: 0.1dev
Summary: ZCML Directive to Define Configuration Strings for Dropdown Lists
Home-page: http://www.timecastle.net
Author: Jeff Rush
Author-email: jeff@taupro.com
License: ZPL 2.1
Keywords: zcml utility zope
Platform: UNKNOWN
Classifier: Development Status :: 2 - Pre-Alpha
Classifier: Environment :: Web Environment
Classifier: Framework :: Zope2
Classifier: Intended Audience :: Developers
Classifier: License :: OSI Approved :: Zope Public License
Classifier: Natural Language :: English
Classifier: Operating System :: OS Independent
Classifier: Programming Language :: Python
Classifier: Topic :: Internet :: WWW/HTTP
